project/ShiftRight.v
module ShiftRight(
     // 4-bit input and output
        input wire [3:0] A, 
        output wire [3:0] o
);
       
    
        //(right shift by 1 bit)
       assign o = {1'b0, A[3:1] }; //slice A from 1 to 3 bits and concatinate 0 in front of A

endmodule

project/NorGate.v
module NorGate(A, B, o);

input wire A, B;
output wire o;

assign o = ~ (A | B);

endmodule

project/NandGate.v
module NandGate(A, B, o);

input wire A, B;
output wire o;

assign o = ~ (A & B);

endmodule

project/NotGate.v
module NotGate(input wire A, output wire o);

    assign o = ~A;

endmodule

project/Testbench.v
module Testbench;

//Inputs
reg A;
reg B;
reg [3:0] A_4bit;

//Outputs
wire o_not;
wire o_nand;
wire o_nor;
wire [3:0] o_shift;

// Instantiate modules
NotGate not_gate(.A(A), .o(o_not));
NandGate nand_gate(.A(A), .B(B), .o(o_nand));
NorGate nor_gate(.A(A), .B(B), .o(o_nor));
ShiftRight shift_right(.A(A_4bit), .o(o_shift));

// Testbench stimulus

initial begin
    //create VCD file
    $dumpfile("simulation.vcd");
    $dumpvars; 

    //test the NOT gate
    A = 1'b0;
    #10; //wait for 5 time units
    A = 1'b1;
    #10;

    // test the NAND gate
    A = 1'b0;
    B = 1'b0;
    #10;
    A = 1'b0;
    B = 1'b1;
    #10;

    // test the NOR gate
    A = 1'b0;
    B = 1'b0;
    #10;
    A = 1'b0;
    B = 1'b1;
    #10;

    // test the 4-bit right shift 
    A_4bit = 4'b1010;
    #10;
    A_4bit = 4'b0110;
    #10;

    $finish;
end
endmodule

project/simulation.vcd
$date
	Mon Sep 11 23:29:52 2023
$end
$version
	Icarus Verilog
$end
$timescale
	1s
$end
$scope module Testbench $end
$var wire 4 ! o_shift [3:0] $end
$var wire 1 " o_not $end
$var wire 1 # o_nor $end
$var wire 1 $ o_nand $end
$var reg 1 % A $end
$var reg 4 & A_4bit [3:0] $end
$var reg 1 ' B $end
$scope module nand_gate $end
$var wire 1 % A $end
$var wire 1 ' B $end
$var wire 1 $ o $end
$upscope $end
$scope module nor_gate $end
$var wire 1 % A $end
$var wire 1 ' B $end
$var wire 1 # o $end
$upscope $end
$scope module not_gate $end
$var wire 1 % A $end
$var wire 1 " o $end
$upscope $end
$scope module shift_right $end
$var wire 4 ( A [3:0] $end
$var wire 4 ) o [3:0] $end
$upscope $end
$upscope $end
$enddefinitions $end
$comment Show the parameter values. $end
$dumpall
$end
#0
$dumpvars
b0xxx )
bx (
x'
bx &
0%
1$
x#
1"
b0xxx !
$end
#10
x$
0#
0"
1%
#20
1$
1#
1"
0'
0%
#30
0#
1'
#40
1#
0'
#50
0#
1'
#60
b101 !
b101 )
b1010 &
b1010 (
#70
b11 !
b11 )
b110 &
b110 (
